{
  "enabled": true,

  "title": "Global Catastrophe Bond Intelligence Platform",

  "subtitle": "Data, analytics, and policy insights on catastrophe bonds and sovereign disaster risk financing.",

  "tagline": "A professional intelligence platform for catastrophe bonds, insurance-linked securities, and sovereign disaster risk transfer.",

  "description": "Explore global catastrophe bond transactions, analyze sovereign risk transfer strategies, and access structured intelligence on disaster risk financing and capital markets.",

  "value_proposition": [
    "Comprehensive database of catastrophe bond transactions",
    "Dedicated analysis of sovereign catastrophe bond programs",
    "Structured financial data for market analytics",
    "Policy insights for disaster risk financing"
  ],

  "background_type": "video",

  "background_video": "/videos/hero/final-globe-scene.mp4",

  "primary_call_to_action": {
    "label": "Explore Sovereign Cases",
    "url": "/sovereign-cases"
  },

  "secondary_call_to_action": {
    "label": "Global Market Analytics",
    "url": "/market"
  },

  "tertiary_call_to_action": {
    "label": "Israel Policy Lab",
    "url": "/israel-lab"
  }
}