{
  "generated_at": "2026-03-18T07:02:10.094Z",
  "countries": [
    {
      "slug": "canada",
      "country_name": "Canada",
      "region": "North America",
      "deal_count": 20,
      "total_volume_usd": 3660000000,
      "total_volume_musd": 3660,
      "latest_issue_year": 2026,
      "main_peril": "Multi-Peril",
      "sovereign_flag": false,
      "sovereign_activity_summary": "No sovereign issuance recorded.",
      "market_segment_breakdown": [
        {
          "segment": "Sovereign",
          "count": 0
        },
        {
          "segment": "Non-Sovereign",
          "count": 20
        }
      ],
      "trigger_breakdown": [
        {
          "trigger": "Indemnity",
          "count": 11
        },
        {
          "trigger": "Industry Loss",
          "count": 9
        }
      ],
      "yearly_issuance": [
        {
          "year": 2013,
          "count": 1,
          "total_volume_usd": 75000000
        },
        {
          "year": 2014,
          "count": 1,
          "total_volume_usd": 500000000
        },
        {
          "year": 2021,
          "count": 1,
          "total_volume_usd": 300000000
        },
        {
          "year": 2022,
          "count": 1,
          "total_volume_usd": 150000000
        },
        {
          "year": 2023,
          "count": 3,
          "total_volume_usd": 525000000
        },
        {
          "year": 2024,
          "count": 4,
          "total_volume_usd": 730000000
        },
        {
          "year": 2025,
          "count": 6,
          "total_volume_usd": 915000000
        },
        {
          "year": 2026,
          "count": 3,
          "total_volume_usd": 465000000
        }
      ]
    },
    {
      "slug": "chile",
      "country_name": "Chile",
      "region": "Global",
      "deal_count": 2,
      "total_volume_usd": 850000000,
      "total_volume_musd": 850,
      "latest_issue_year": 2023,
      "main_peril": "Earthquake",
      "sovereign_flag": true,
      "sovereign_activity_summary": "Sovereign issuance observed across 2 deals.",
      "market_segment_breakdown": [
        {
          "segment": "Sovereign",
          "count": 2
        },
        {
          "segment": "Non-Sovereign",
          "count": 0
        }
      ],
      "trigger_breakdown": [
        {
          "trigger": "Parametric",
          "count": 2
        }
      ],
      "yearly_issuance": [
        {
          "year": 2018,
          "count": 1,
          "total_volume_usd": 500000000
        },
        {
          "year": 2023,
          "count": 1,
          "total_volume_usd": 350000000
        }
      ]
    },
    {
      "slug": "colombia",
      "country_name": "Colombia",
      "region": "Global",
      "deal_count": 1,
      "total_volume_usd": 400000000,
      "total_volume_musd": 400,
      "latest_issue_year": 2018,
      "main_peril": "Earthquake",
      "sovereign_flag": true,
      "sovereign_activity_summary": "Sovereign issuance observed across 1 deals.",
      "market_segment_breakdown": [
        {
          "segment": "Sovereign",
          "count": 1
        },
        {
          "segment": "Non-Sovereign",
          "count": 0
        }
      ],
      "trigger_breakdown": [
        {
          "trigger": "Parametric",
          "count": 1
        }
      ],
      "yearly_issuance": [
        {
          "year": 2018,
          "count": 1,
          "total_volume_usd": 400000000
        }
      ]
    },
    {
      "slug": "israel",
      "country_name": "Israel",
      "region": "Middle East",
      "deal_count": 1,
      "total_volume_usd": 100000000,
      "total_volume_musd": 100,
      "latest_issue_year": 2025,
      "main_peril": "Earthquake",
      "sovereign_flag": false,
      "sovereign_activity_summary": "No sovereign issuance recorded.",
      "market_segment_breakdown": [
        {
          "segment": "Sovereign",
          "count": 0
        },
        {
          "segment": "Non-Sovereign",
          "count": 1
        }
      ],
      "trigger_breakdown": [
        {
          "trigger": "Indemnity",
          "count": 1
        }
      ],
      "yearly_issuance": [
        {
          "year": 2025,
          "count": 1,
          "total_volume_usd": 100000000
        }
      ]
    },
    {
      "slug": "jamaica",
      "country_name": "Jamaica",
      "region": "Global",
      "deal_count": 2,
      "total_volume_usd": 335000000,
      "total_volume_musd": 335,
      "latest_issue_year": 2024,
      "main_peril": "Hurricane / Wind",
      "sovereign_flag": true,
      "sovereign_activity_summary": "Sovereign issuance observed across 2 deals.",
      "market_segment_breakdown": [
        {
          "segment": "Sovereign",
          "count": 2
        },
        {
          "segment": "Non-Sovereign",
          "count": 0
        }
      ],
      "trigger_breakdown": [
        {
          "trigger": "Parametric",
          "count": 2
        }
      ],
      "yearly_issuance": [
        {
          "year": 2021,
          "count": 1,
          "total_volume_usd": 185000000
        },
        {
          "year": 2024,
          "count": 1,
          "total_volume_usd": 150000000
        }
      ]
    },
    {
      "slug": "japan",
      "country_name": "Japan",
      "region": "Apac",
      "deal_count": 87,
      "total_volume_usd": 15729464850.13624,
      "total_volume_musd": 15729.46485013624,
      "latest_issue_year": 2025,
      "main_peril": "Multi-Peril",
      "sovereign_flag": false,
      "sovereign_activity_summary": "No sovereign issuance recorded.",
      "market_segment_breakdown": [
        {
          "segment": "Sovereign",
          "count": 0
        },
        {
          "segment": "Non-Sovereign",
          "count": 87
        }
      ],
      "trigger_breakdown": [
        {
          "trigger": "Hybrid",
          "count": 8
        },
        {
          "trigger": "Indemnity",
          "count": 33
        },
        {
          "trigger": "Industry Loss",
          "count": 8
        },
        {
          "trigger": "Modelled Loss",
          "count": 6
        },
        {
          "trigger": "Parametric",
          "count": 30
        },
        {
          "trigger": "Unknown",
          "count": 2
        }
      ],
      "yearly_issuance": [
        {
          "year": 1997,
          "count": 1,
          "total_volume_usd": 100000000
        },
        {
          "year": 1998,
          "count": 1,
          "total_volume_usd": 80000000
        },
        {
          "year": 1999,
          "count": 2,
          "total_volume_usd": 200000000
        },
        {
          "year": 2000,
          "count": 1,
          "total_volume_usd": 200000000
        },
        {
          "year": 2001,
          "count": 1,
          "total_volume_usd": 150000000
        },
        {
          "year": 2002,
          "count": 3,
          "total_volume_usd": 555000000
        },
        {
          "year": 2003,
          "count": 7,
          "total_volume_usd": 661000000
        },
        {
          "year": 2004,
          "count": 6,
          "total_volume_usd": 310800000
        },
        {
          "year": 2005,
          "count": 4,
          "total_volume_usd": 153000000
        },
        {
          "year": 2006,
          "count": 4,
          "total_volume_usd": 1337500000
        },
        {
          "year": 2007,
          "count": 7,
          "total_volume_usd": 1155000000
        },
        {
          "year": 2008,
          "count": 5,
          "total_volume_usd": 904000000
        },
        {
          "year": 2009,
          "count": 1,
          "total_volume_usd": 113000000
        },
        {
          "year": 2010,
          "count": 4,
          "total_volume_usd": 534500000
        },
        {
          "year": 2011,
          "count": 4,
          "total_volume_usd": 425000000
        },
        {
          "year": 2012,
          "count": 2,
          "total_volume_usd": 430000000
        },
        {
          "year": 2013,
          "count": 1,
          "total_volume_usd": 300000000
        },
        {
          "year": 2014,
          "count": 4,
          "total_volume_usd": 920664850.1362398
        },
        {
          "year": 2015,
          "count": 2,
          "total_volume_usd": 590000000
        },
        {
          "year": 2016,
          "count": 3,
          "total_volume_usd": 1120000000
        },
        {
          "year": 2017,
          "count": 1,
          "total_volume_usd": 480000000
        },
        {
          "year": 2018,
          "count": 3,
          "total_volume_usd": 1220000000
        },
        {
          "year": 2020,
          "count": 2,
          "total_volume_usd": 300000000
        },
        {
          "year": 2021,
          "count": 5,
          "total_volume_usd": 1675000000
        },
        {
          "year": 2022,
          "count": 4,
          "total_volume_usd": 650000000
        },
        {
          "year": 2023,
          "count": 1,
          "total_volume_usd": 225000000
        },
        {
          "year": 2024,
          "count": 3,
          "total_volume_usd": 450000000
        },
        {
          "year": 2025,
          "count": 5,
          "total_volume_usd": 490000000
        }
      ]
    },
    {
      "slug": "mexico",
      "country_name": "Mexico",
      "region": "Latam",
      "deal_count": 7,
      "total_volume_usd": 2150000000,
      "total_volume_musd": 2150,
      "latest_issue_year": 2024,
      "main_peril": "Multi-Peril",
      "sovereign_flag": true,
      "sovereign_activity_summary": "Sovereign issuance observed across 7 deals.",
      "market_segment_breakdown": [
        {
          "segment": "Sovereign",
          "count": 7
        },
        {
          "segment": "Non-Sovereign",
          "count": 0
        }
      ],
      "trigger_breakdown": [
        {
          "trigger": "Parametric",
          "count": 7
        }
      ],
      "yearly_issuance": [
        {
          "year": 2006,
          "count": 1,
          "total_volume_usd": 160000000
        },
        {
          "year": 2009,
          "count": 1,
          "total_volume_usd": 290000000
        },
        {
          "year": 2017,
          "count": 1,
          "total_volume_usd": 360000000
        },
        {
          "year": 2018,
          "count": 1,
          "total_volume_usd": 260000000
        },
        {
          "year": 2020,
          "count": 1,
          "total_volume_usd": 485000000
        },
        {
          "year": 2024,
          "count": 2,
          "total_volume_usd": 595000000
        }
      ]
    },
    {
      "slug": "not-stated",
      "country_name": "Not Stated",
      "region": "Global",
      "deal_count": 267,
      "total_volume_usd": 59172664100.81744,
      "total_volume_musd": 59172.664100817434,
      "latest_issue_year": 2026,
      "main_peril": "Hurricane / Wind",
      "sovereign_flag": true,
      "sovereign_activity_summary": "Sovereign issuance observed across 2 deals.",
      "market_segment_breakdown": [
        {
          "segment": "Sovereign",
          "count": 2
        },
        {
          "segment": "Non-Sovereign",
          "count": 265
        }
      ],
      "trigger_breakdown": [
        {
          "trigger": "Indemnity",
          "count": 210
        },
        {
          "trigger": "Industry Loss",
          "count": 31
        },
        {
          "trigger": "Loss Ratio Trigger",
          "count": 1
        },
        {
          "trigger": "Modelled Loss",
          "count": 2
        },
        {
          "trigger": "Parametric",
          "count": 22
        },
        {
          "trigger": "Unknown",
          "count": 1
        }
      ],
      "yearly_issuance": [
        {
          "year": 1996,
          "count": 1,
          "total_volume_usd": 68500000
        },
        {
          "year": 1997,
          "count": 1,
          "total_volume_usd": 137000000
        },
        {
          "year": 1998,
          "count": 3,
          "total_volume_usd": 290100000
        },
        {
          "year": 2000,
          "count": 3,
          "total_volume_usd": 369000000
        },
        {
          "year": 2001,
          "count": 2,
          "total_volume_usd": 265000000
        },
        {
          "year": 2002,
          "count": 2,
          "total_volume_usd": 375000000
        },
        {
          "year": 2003,
          "count": 4,
          "total_volume_usd": 678000000
        },
        {
          "year": 2004,
          "count": 2,
          "total_volume_usd": 300000000
        },
        {
          "year": 2005,
          "count": 2,
          "total_volume_usd": 621893732.9700272
        },
        {
          "year": 2006,
          "count": 8,
          "total_volume_usd": 1421536103.5422344
        },
        {
          "year": 2007,
          "count": 8,
          "total_volume_usd": 1769600000
        },
        {
          "year": 2008,
          "count": 1,
          "total_volume_usd": 258000000
        },
        {
          "year": 2009,
          "count": 3,
          "total_volume_usd": 575000000
        },
        {
          "year": 2010,
          "count": 5,
          "total_volume_usd": 1005000000
        },
        {
          "year": 2011,
          "count": 6,
          "total_volume_usd": 1061000000
        },
        {
          "year": 2012,
          "count": 6,
          "total_volume_usd": 1740000000
        },
        {
          "year": 2013,
          "count": 10,
          "total_volume_usd": 2396578746.5940056
        },
        {
          "year": 2014,
          "count": 6,
          "total_volume_usd": 1237549046.321526
        },
        {
          "year": 2015,
          "count": 7,
          "total_volume_usd": 1916893732.9700272
        },
        {
          "year": 2016,
          "count": 3,
          "total_volume_usd": 851539509.5367848
        },
        {
          "year": 2017,
          "count": 14,
          "total_volume_usd": 3651272479.564033
        },
        {
          "year": 2018,
          "count": 7,
          "total_volume_usd": 1404000000
        },
        {
          "year": 2019,
          "count": 9,
          "total_volume_usd": 1532937329.7002723
        },
        {
          "year": 2020,
          "count": 17,
          "total_volume_usd": 3674393732.970027
        },
        {
          "year": 2021,
          "count": 20,
          "total_volume_usd": 4259652588.555858
        },
        {
          "year": 2022,
          "count": 19,
          "total_volume_usd": 3036000000
        },
        {
          "year": 2023,
          "count": 32,
          "total_volume_usd": 7720667574.931879
        },
        {
          "year": 2024,
          "count": 26,
          "total_volume_usd": 4608675749.3188
        },
        {
          "year": 2025,
          "count": 36,
          "total_volume_usd": 10577873773.84196
        },
        {
          "year": 2026,
          "count": 4,
          "total_volume_usd": 1370000000
        }
      ]
    },
    {
      "slug": "peru",
      "country_name": "Peru",
      "region": "Global",
      "deal_count": 1,
      "total_volume_usd": 200000000,
      "total_volume_musd": 200,
      "latest_issue_year": 2018,
      "main_peril": "Earthquake",
      "sovereign_flag": true,
      "sovereign_activity_summary": "Sovereign issuance observed across 1 deals.",
      "market_segment_breakdown": [
        {
          "segment": "Sovereign",
          "count": 1
        },
        {
          "segment": "Non-Sovereign",
          "count": 0
        }
      ],
      "trigger_breakdown": [
        {
          "trigger": "Parametric",
          "count": 1
        }
      ],
      "yearly_issuance": [
        {
          "year": 2018,
          "count": 1,
          "total_volume_usd": 200000000
        }
      ]
    },
    {
      "slug": "philippines",
      "country_name": "Philippines",
      "region": "Global",
      "deal_count": 1,
      "total_volume_usd": 225000000,
      "total_volume_musd": 225,
      "latest_issue_year": 2019,
      "main_peril": "Earthquake",
      "sovereign_flag": true,
      "sovereign_activity_summary": "Sovereign issuance observed across 1 deals.",
      "market_segment_breakdown": [
        {
          "segment": "Sovereign",
          "count": 1
        },
        {
          "segment": "Non-Sovereign",
          "count": 0
        }
      ],
      "trigger_breakdown": [
        {
          "trigger": "Modelled Loss",
          "count": 1
        }
      ],
      "yearly_issuance": [
        {
          "year": 2019,
          "count": 1,
          "total_volume_usd": 225000000
        }
      ]
    },
    {
      "slug": "puerto-rico",
      "country_name": "Puerto Rico",
      "region": "Global",
      "deal_count": 1,
      "total_volume_usd": 85000000,
      "total_volume_musd": 85,
      "latest_issue_year": 2024,
      "main_peril": "Multi-Peril",
      "sovereign_flag": true,
      "sovereign_activity_summary": "Sovereign issuance observed across 1 deals.",
      "market_segment_breakdown": [
        {
          "segment": "Sovereign",
          "count": 1
        },
        {
          "segment": "Non-Sovereign",
          "count": 0
        }
      ],
      "trigger_breakdown": [
        {
          "trigger": "Parametric",
          "count": 1
        }
      ],
      "yearly_issuance": [
        {
          "year": 2024,
          "count": 1,
          "total_volume_usd": 85000000
        }
      ]
    },
    {
      "slug": "united-states",
      "country_name": "United States",
      "region": "North America",
      "deal_count": 440,
      "total_volume_usd": 102455986539.50954,
      "total_volume_musd": 102455.98653950954,
      "latest_issue_year": 2026,
      "main_peril": "Multi-Peril",
      "sovereign_flag": true,
      "sovereign_activity_summary": "Sovereign issuance observed across 5 deals.",
      "market_segment_breakdown": [
        {
          "segment": "Sovereign",
          "count": 5
        },
        {
          "segment": "Non-Sovereign",
          "count": 435
        }
      ],
      "trigger_breakdown": [
        {
          "trigger": "Hybrid",
          "count": 2
        },
        {
          "trigger": "Indemnity",
          "count": 219
        },
        {
          "trigger": "Industry Loss",
          "count": 176
        },
        {
          "trigger": "Modelled Loss",
          "count": 15
        },
        {
          "trigger": "Parametric",
          "count": 25
        },
        {
          "trigger": "Rms",
          "count": 1
        },
        {
          "trigger": "Unknown",
          "count": 2
        }
      ],
      "yearly_issuance": [
        {
          "year": 1997,
          "count": 1,
          "total_volume_usd": 480000000
        },
        {
          "year": 1998,
          "count": 4,
          "total_volume_usd": 775000000
        },
        {
          "year": 1999,
          "count": 4,
          "total_volume_usd": 563000000
        },
        {
          "year": 2000,
          "count": 1,
          "total_volume_usd": 200000000
        },
        {
          "year": 2001,
          "count": 6,
          "total_volume_usd": 848300000
        },
        {
          "year": 2002,
          "count": 2,
          "total_volume_usd": 158000000
        },
        {
          "year": 2003,
          "count": 1,
          "total_volume_usd": 160000000
        },
        {
          "year": 2004,
          "count": 2,
          "total_volume_usd": 475000000
        },
        {
          "year": 2005,
          "count": 5,
          "total_volume_usd": 1216000000
        },
        {
          "year": 2006,
          "count": 14,
          "total_volume_usd": 2044500000
        },
        {
          "year": 2007,
          "count": 14,
          "total_volume_usd": 3126380000
        },
        {
          "year": 2008,
          "count": 7,
          "total_volume_usd": 1410000000
        },
        {
          "year": 2009,
          "count": 13,
          "total_volume_usd": 2422000000
        },
        {
          "year": 2010,
          "count": 14,
          "total_volume_usd": 3295000000
        },
        {
          "year": 2011,
          "count": 13,
          "total_volume_usd": 2947000000
        },
        {
          "year": 2012,
          "count": 17,
          "total_volume_usd": 3682000000
        },
        {
          "year": 2013,
          "count": 20,
          "total_volume_usd": 4597000000
        },
        {
          "year": 2014,
          "count": 17,
          "total_volume_usd": 3845000000
        },
        {
          "year": 2015,
          "count": 17,
          "total_volume_usd": 3752500000
        },
        {
          "year": 2016,
          "count": 15,
          "total_volume_usd": 3895000000
        },
        {
          "year": 2017,
          "count": 19,
          "total_volume_usd": 5835500000
        },
        {
          "year": 2018,
          "count": 18,
          "total_volume_usd": 5510000000
        },
        {
          "year": 2019,
          "count": 14,
          "total_volume_usd": 3575000000
        },
        {
          "year": 2020,
          "count": 29,
          "total_volume_usd": 6855000000
        },
        {
          "year": 2021,
          "count": 25,
          "total_volume_usd": 6260000000
        },
        {
          "year": 2022,
          "count": 26,
          "total_volume_usd": 5755000000
        },
        {
          "year": 2023,
          "count": 34,
          "total_volume_usd": 6850000000
        },
        {
          "year": 2024,
          "count": 33,
          "total_volume_usd": 7128670299.72752
        },
        {
          "year": 2025,
          "count": 43,
          "total_volume_usd": 11040136239.782017
        },
        {
          "year": 2026,
          "count": 12,
          "total_volume_usd": 3755000000
        }
      ]
    }
  ]
}
